{
  "id": "e6e253fb0eec5b7b",
  "title": "郑栅洁主任主持召开民营企业座谈会",
  "url": "http://www.ndrc.gov.cn/xwdt/xwfb/202604/t20260420_1404786.html \"郑栅洁主任主持召开民营企业座谈会 围绕准确把握当前经济形势、积极应对外部环境变化听取意见建议\"",
  "source": "国家发改委-通知公告",
  "source_level": "P0",
  "published_at": "",
  "parsed_at": "2026-05-15T02:01:46.213711+00:00",
  "confidence": 0.6,
  "parse_error": null,
  "级别": null,
  "地区": [
    "全国"
  ],
  "主管部门": [
    "发改委"
  ],
  "发布时间": null,
  "申报截止时间": null,
  "政策类型": null,
  "支持方向": [],
  "支持金额": {
    "描述": null,
    "金额": null,
    "单位": null
  },
  "申报条件": {
    "必要资质": [],
    "规模要求": null,
    "投资要求": null
  },
  "材料要求": [],
  "评审方式": null,
  "是否后补贴": null,
  "验收要求": null,
  "风险提示": [
    "该政策原文页面返回404错误，政策内容无法获取",
    "URL链接已失效或页面不存在"
  ],
  "政策原文关键词": [],
  "适合申报企业": []
}